bedrock_bot/__init__.py
bedrock_bot/cli.py
bedrock_bot/models/__init__.py
bedrock_bot/models/base_model.py
bedrock_bot/models/claude.py
bedrock_bot/models/nova.py
bedrock_bot/util.py
bedrock_bot-1.6.1.dist-info/LICENSE
bedrock_bot-1.6.1.dist-info/METADATA
bedrock_bot-1.6.1.dist-info/WHEEL
bedrock_bot-1.6.1.dist-info/entry_points.txt
bedrock_bot-1.6.1.dist-info/RECORD
