Metadata-Version: 2.3
Name: bedrock-bot
Version: 1.6.1
Summary: 
Author: Justin Dray
Author-email: justin@dray.be
Requires-Python: >=3.8,<4.0
Classifier: Programming Language :: Python :: 3
Classifier: Programming Language :: Python :: 3.8
Classifier: Programming Language :: Python :: 3.9
Classifier: Programming Language :: Python :: 3.10
Classifier: Programming Language :: Python :: 3.11
Classifier: Programming Language :: Python :: 3.12
Classifier: Programming Language :: Python :: 3.13
Requires-Dist: boto3 (>=1.35.67,<2.0.0)
Requires-Dist: click (>=8.0.0,<9.0.0)
Requires-Dist: rich (>=13.0.0,<14.0.0)
